accelbyte_py_sdk/api/challenge/__init__.py
accelbyte_py_sdk/api/challenge/errors.py
accelbyte_py_sdk/api/challenge/models/__init__.py
accelbyte_py_sdk/api/challenge/models/iam_error_response.py
accelbyte_py_sdk/api/challenge/models/iam_permission.py
accelbyte_py_sdk/api/challenge/models/model_challenge_reference.py
accelbyte_py_sdk/api/challenge/models/model_challenge_response.py
accelbyte_py_sdk/api/challenge/models/model_claim_user_rewards_by_goal_code_request.py
accelbyte_py_sdk/api/challenge/models/model_claim_user_rewards_req.py
accelbyte_py_sdk/api/challenge/models/model_claim_users_rewards_request.py
accelbyte_py_sdk/api/challenge/models/model_claim_users_rewards_response.py
accelbyte_py_sdk/api/challenge/models/model_claimable_user_reward.py
accelbyte_py_sdk/api/challenge/models/model_create_challenge_request.py
accelbyte_py_sdk/api/challenge/models/model_create_goal_request.py
accelbyte_py_sdk/api/challenge/models/model_evaluate_player_progression_request.py
accelbyte_py_sdk/api/challenge/models/model_get_goals_response.py
accelbyte_py_sdk/api/challenge/models/model_goal_in_schedules_response.py
accelbyte_py_sdk/api/challenge/models/model_goal_meta.py
accelbyte_py_sdk/api/challenge/models/model_goal_order.py
accelbyte_py_sdk/api/challenge/models/model_goal_progression_response.py
accelbyte_py_sdk/api/challenge/models/model_goal_response.py
accelbyte_py_sdk/api/challenge/models/model_goal_schedule.py
accelbyte_py_sdk/api/challenge/models/model_goal_schedule_request.py
accelbyte_py_sdk/api/challenge/models/model_item_reference.py
accelbyte_py_sdk/api/challenge/models/model_item_reference_response.py
accelbyte_py_sdk/api/challenge/models/model_list_challenge_response.py
accelbyte_py_sdk/api/challenge/models/model_list_periods_response.py
accelbyte_py_sdk/api/challenge/models/model_list_schedule_by_goal_response.py
accelbyte_py_sdk/api/challenge/models/model_list_schedules_response.py
accelbyte_py_sdk/api/challenge/models/model_list_user_rewards_response.py
accelbyte_py_sdk_service_challenge-0.18.0.dist-info/METADATA
accelbyte_py_sdk_service_challenge-0.18.0.dist-info/WHEEL
accelbyte_py_sdk_service_challenge-0.18.0.dist-info/top_level.txt
accelbyte_py_sdk_service_challenge-0.18.0.dist-info/RECORD
