Metadata-Version: 2.4
Name: accelbyte-py-sdk-service-challenge
Version: 0.18.0
Summary: AccelByte Python SDK - AccelByte Gaming Services Challenge Service
Requires-Python: >=3.9
Requires-Dist: accelbyte-py-sdk-core
